apiverve_websitereadability/__init__.py
apiverve_websitereadability/apiClient.py
apiverve_websitereadability/exceptions.py
apiverve_websitereadability/setup.py
apiverve_websitereadability/setup_dep.py
apiverve_websitereadability/tests/__init__.py
apiverve_websitereadability/tests/test_api.py
apiverve_websitereadability-1.1.5.dist-info/LICENSE
apiverve_websitereadability-1.1.5.dist-info/METADATA
apiverve_websitereadability-1.1.5.dist-info/WHEEL
apiverve_websitereadability-1.1.5.dist-info/top_level.txt
apiverve_websitereadability-1.1.5.dist-info/RECORD
